[
  {
    "paperURL": "/wiki/Kinh_D%C6%B0%C6%A1ng_V%C6%B0%C6%A1ng",
    "mieuHieu": "không có",
    "thuyHieu": "Kinh Dương Vương[j]",
    "nienHieu": "không có",
    "tenHuy": "Lộc Tục[3]",
    "theThu": "Khai sáng triều đại, con thứ Đế Minh, em Đế Nghi",
    "namTriVi": "2879 TCN–2794 TCN",
    "ten": "Kinh Dương Vương"
  },
  {
    "paperURL": "/wiki/L%E1%BA%A1c_Long_Qu%C3%A2n",
    "mieuHieu": "không có",
    "thuyHieu": "Lạc Long Quân[l]",
    "nienHieu": "không có",
    "tenHuy": "Sùng Lãm[3]",
    "theThu": "Con Kinh Dương Vương",
    "namTriVi": "2525 TCN–2253 TCN",
    "ten": "Lạc Long Quân"
  },
  {
    "paperURL": "/wiki/H%C3%B9ng_V%C6%B0%C6%A1ng_th%E1%BB%A9_I",
    "mieuHieu": "không có",
    "thuyHieu": "Hùng Quốc Vương[m]",
    "nienHieu": "không có",
    "tenHuy": "không rõ",
    "theThu": "Con trưởng Lạc Long Quân",
    "namTriVi": "?",
    "ten": "Hùng Vương thứ nhất"
  },
  {
    "paperURL": "/wiki/H%C3%B9ng_V%C6%B0%C6%A1ng_th%E1%BB%A9_II",
    "mieuHieu": "không có",
    "thuyHieu": "Hùng Hiền Vương[m]",
    "nienHieu": "không có",
    "tenHuy": "không rõ",
    "theThu": "",
    "namTriVi": "?–?",
    "ten": "Hùng Vương thứ hai"
  },
  {
    "paperURL": "/wiki/H%C3%B9ng_V%C6%B0%C6%A1ng_th%E1%BB%A9_III",
    "mieuHieu": "không có",
    "thuyHieu": "Hùng Lân Vương[m]",
    "nienHieu": "không có",
    "tenHuy": "không rõ",
    "theThu": "",
    "namTriVi": "?–?",
    "ten": "Hùng Vương thứ ba"
  },
  {
    "paperURL": "/wiki/H%C3%B9ng_V%C6%B0%C6%A1ng_th%E1%BB%A9_IV",
    "mieuHieu": "không có",
    "thuyHieu": "Hùng Diệp Vương[m]",
    "nienHieu": "không có",
    "tenHuy": "không rõ",
    "theThu": "",
    "namTriVi": "?–?",
    "ten": "Hùng Vương thứ tư"
  },
  {
    "paperURL": "/w/index.php?title\u003dH%C3%B9ng_V%C6%B0%C6%A1ng_th%E1%BB%A9_5\u0026action\u003dedit\u0026redlink\u003d1",
    "mieuHieu": "không có",
    "thuyHieu": "Hùng Hy Vương[m]",
    "nienHieu": "không có",
    "tenHuy": "không rõ",
    "theThu": "",
    "namTriVi": "?–?",
    "ten": "Hùng Vương thứ năm"
  },
  {
    "paperURL": "/wiki/H%C3%B9ng_V%C6%B0%C6%A1ng_th%E1%BB%A9_VI",
    "mieuHieu": "không có",
    "thuyHieu": "Hùng Huy Vương[m]",
    "nienHieu": "không có",
    "tenHuy": "không rõ",
    "theThu": "",
    "namTriVi": "?–?",
    "ten": "Hùng Vương thứ sáu"
  },
  {
    "paperURL": "/wiki/Lang_Li%C3%AAu",
    "mieuHieu": "không có",
    "thuyHieu": "Hùng Chiêu Vương[m]",
    "nienHieu": "không có",
    "tenHuy": "Lang Liêu[6]",
    "theThu": "",
    "namTriVi": "?–?",
    "ten": "Hùng Vương thứ bảy"
  },
  {
    "paperURL": "/wiki/H%C3%B9ng_V%C6%B0%C6%A1ng_th%E1%BB%A9_VIII",
    "mieuHieu": "không có",
    "thuyHieu": "Hùng Vĩ Vương[m]",
    "nienHieu": "không có",
    "tenHuy": "Thừa Vân Lang",
    "theThu": "",
    "namTriVi": "?–?",
    "ten": "Hùng Vương thứ tám"
  },
  {
    "paperURL": "/wiki/H%C3%B9ng_V%C6%B0%C6%A1ng_th%E1%BB%A9_IX",
    "mieuHieu": "không có",
    "thuyHieu": "Hùng Định Vương[m]",
    "nienHieu": "không có",
    "tenHuy": "Quân Lang",
    "theThu": "",
    "namTriVi": "?–?",
    "ten": "Hùng Vương thứ chín"
  },
  {
    "paperURL": "/wiki/H%C3%B9ng_V%C6%B0%C6%A1ng_th%E1%BB%A9_X",
    "mieuHieu": "không có",
    "thuyHieu": "Hùng Uy Vương[m]",
    "nienHieu": "không có",
    "tenHuy": "Hùng Hải Lang",
    "theThu": "",
    "namTriVi": "?–?",
    "ten": "Hùng Vương thứ mười"
  },
  {
    "paperURL": "/wiki/H%C3%B9ng_V%C6%B0%C6%A1ng_th%E1%BB%A9_XI",
    "mieuHieu": "không có",
    "thuyHieu": "Hùng Trinh Vương[m]",
    "nienHieu": "không có",
    "tenHuy": "Hưng Đức Lang",
    "theThu": "",
    "namTriVi": "?–?",
    "ten": "Hùng Vương thứ 11"
  },
  {
    "paperURL": "/wiki/H%C3%B9ng_V%C6%B0%C6%A1ng_th%E1%BB%A9_XII",
    "mieuHieu": "không có",
    "thuyHieu": "Hùng Vũ Vương[m]",
    "nienHieu": "không có",
    "tenHuy": "không rõ",
    "theThu": "",
    "namTriVi": "?–?",
    "ten": "Hùng Vương thứ 12"
  },
  {
    "paperURL": "/wiki/H%C3%B9ng_V%C6%B0%C6%A1ng_th%E1%BB%A9_XIII",
    "mieuHieu": "không có",
    "thuyHieu": "Hùng Việt Vương[m]",
    "nienHieu": "không có",
    "tenHuy": "Tuấn Lang",
    "theThu": "",
    "namTriVi": "?–?",
    "ten": "Hùng Vương thứ 13"
  },
  {
    "paperURL": "/wiki/H%C3%B9ng_V%C6%B0%C6%A1ng_th%E1%BB%A9_XIV",
    "mieuHieu": "không có",
    "thuyHieu": "Hùng Anh Vương[m]",
    "nienHieu": "không có",
    "tenHuy": "Chân Nhân Lang",
    "theThu": "",
    "namTriVi": "?–?",
    "ten": "Hùng Vương thứ 14"
  },
  {
    "paperURL": "/wiki/H%C3%B9ng_V%C6%B0%C6%A1ng_th%E1%BB%A9_XV",
    "mieuHieu": "không có",
    "thuyHieu": "Hùng Triêu Vương[m]",
    "nienHieu": "không có",
    "tenHuy": "Cảnh Chiêu Lang",
    "theThu": "",
    "namTriVi": "?–?",
    "ten": "Hùng Vương thứ 15"
  },
  {
    "paperURL": "/wiki/H%C3%B9ng_V%C6%B0%C6%A1ng_th%E1%BB%A9_XVI",
    "mieuHieu": "không có",
    "thuyHieu": "Hùng Tạo Vương",
    "nienHieu": "không có",
    "tenHuy": "Đức Quân Lang",
    "theThu": "",
    "namTriVi": "?–?",
    "ten": "Hùng Vương thứ 16"
  },
  {
    "paperURL": "/wiki/H%C3%B9ng_V%C6%B0%C6%A1ng_th%E1%BB%A9_XVII",
    "mieuHieu": "không có",
    "thuyHieu": "Hùng Nghị Vương[m]",
    "nienHieu": "không có",
    "tenHuy": "không rõ",
    "theThu": "",
    "namTriVi": "?–?",
    "ten": "Hùng Vương thứ 17"
  },
  {
    "paperURL": "/wiki/H%C3%B9ng_V%C6%B0%C6%A1ng_th%E1%BB%A9_XVIII",
    "mieuHieu": "không có",
    "thuyHieu": "Hùng Duệ Vương[m] Hùng Tuyền Vương[7]",
    "nienHieu": "không có",
    "tenHuy": "không rõ",
    "theThu": "",
    "namTriVi": "?–258 TCN",
    "ten": "Hùng Vương thứ 18"
  },
  {
    "paperURL": "/w/index.php?title\u003dH%C3%B9ng_V%C6%B0%C6%A1ng_th%E1%BB%A9_XIX\u0026action\u003dedit\u0026redlink\u003d1",
    "mieuHieu": "không có",
    "thuyHieu": "Hùng Kính Vương[m]",
    "nienHieu": "không có",
    "tenHuy": "Huệ Lang",
    "theThu": "",
    "namTriVi": "?–6 năm",
    "ten": "Hùng Vương thứ 19[8]"
  },
  {
    "paperURL": "/wiki/Tri%E1%BB%87u_V%C5%A9_V%C6%B0%C6%A1ng",
    "mieuHieu": "không có[q]",
    "thuyHieu": "Vũ Vương Vũ Đế[r]",
    "nienHieu": "không có",
    "tenHuy": "Triệu Đà[3]",
    "theThu": "Dòng dõi nước Triệu thời Chiến Quốc, khai sáng triều đại.[s]",
    "namTriVi": "204—137TCN",
    "ten": "Triệu Vũ Vương[2]"
  },
  {
    "paperURL": "/wiki/Tri%E1%BB%87u_V%C4%83n_V%C6%B0%C6%A1ng",
    "mieuHieu": "không có",
    "thuyHieu": "Văn Vương Văn Đế[t]",
    "nienHieu": "không có",
    "tenHuy": "Triệu Hồ[9] Triệu Muội[3]",
    "theThu": "Cháu nội Triệu Đà, con Triệu Trọng Thủy.",
    "namTriVi": "137—125TCN",
    "ten": "Triệu Văn Vương[2]"
  },
  {
    "paperURL": "/wiki/Tri%E1%BB%87u_Minh_V%C6%B0%C6%A1ng",
    "mieuHieu": "không có",
    "thuyHieu": "Minh Vương",
    "nienHieu": "không có",
    "tenHuy": "Triệu Anh Tề[3]",
    "theThu": "Con Triệu Hồ",
    "namTriVi": "125—113TCN",
    "ten": "Triệu Minh Vương[2]"
  },
  {
    "paperURL": "/wiki/Tri%E1%BB%87u_Ai_V%C6%B0%C6%A1ng",
    "mieuHieu": "không có",
    "thuyHieu": "Ai Vương",
    "nienHieu": "không có",
    "tenHuy": "Triệu Hưng[3]",
    "theThu": "Con thứ Triệu Anh Tề",
    "namTriVi": "113—112TCN",
    "ten": "Triệu Ai Vương[2]"
  },
  {
    "paperURL": "/wiki/Tri%E1%BB%87u_D%C6%B0%C6%A1ng_V%C6%B0%C6%A1ng",
    "mieuHieu": "không có",
    "thuyHieu": "Dương Vương Thuật Dương Vương Vệ Dương vương Vệ Dương hầu[u]",
    "nienHieu": "không có",
    "tenHuy": "Triệu Kiến Đức[3]",
    "theThu": "Con trưởng Triệu Anh Tề, anh Triệu Hưng.",
    "namTriVi": "112—111TCN",
    "ten": "Triệu Dương Vương[2]"
  },
  {
    "paperURL": "/wiki/Hai_B%C3%A0_Tr%C6%B0ng",
    "mieuHieu": "không có",
    "thuyHieu": "Trinh Linh Chi Phu Nhân[v]",
    "nienHieu": "không có",
    "tenHuy": "Trưng Trắc[12] (徵側) Lạc Trắc[12]",
    "theThu": "Vợ Thi Sách, sáng lập triều đại",
    "namTriVi": "40—43",
    "ten": "Trưng Vương[13]"
  },
  {
    "paperURL": "/wiki/L%C3%BD_Nam_%C4%90%E1%BA%BF",
    "mieuHieu": "không có",
    "thuyHieu": "Nam Đế, Nam Việt Đế[w]",
    "nienHieu": "Thiên Đức (544–548)[14]",
    "tenHuy": "Lý Bí[14] Lý Bôn[14] (李賁)",
    "theThu": "Nổi dậy tự lập, khai sáng triều đại[15]",
    "namTriVi": "544—548",
    "ten": "Lý Nam Đế"
  },
  {
    "paperURL": "/wiki/Tri%E1%BB%87u_Vi%E1%BB%87t_V%C6%B0%C6%A1ng",
    "mieuHieu": "không có",
    "thuyHieu": "Nam Việt Quốc Vương, Dạ Trạch Vương[y] Thần Vũ Hoàng Đế",
    "nienHieu": "không có[14]",
    "tenHuy": "Triệu Quang Phục[15] (趙光復)",
    "theThu": "Con Thái phó Triệu Túc, được Lý Nam Đế giao toàn bộ quyền hành.[15]",
    "namTriVi": "548—571",
    "ten": "Triệu Việt Vương[x]"
  },
  {
    "paperURL": "/wiki/L%C3%BD_Thi%C3%AAn_B%E1%BA%A3o",
    "mieuHieu": "không có",
    "thuyHieu": "không có[14]",
    "nienHieu": "không có[14]",
    "tenHuy": "Lý Thiên Bảo[14]",
    "theThu": "Anh trai Lý Nam Đế[14]",
    "namTriVi": "549—555",
    "ten": "Đào Lang Vương[z]"
  },
  {
    "paperURL": "/wiki/H%E1%BA%ADu_L%C3%BD_Nam_%C4%90%E1%BA%BF",
    "mieuHieu": "không có",
    "thuyHieu": "Nam Đế[ab] Anh Liệt Nhân Hiếu Khâm Minh Thánh Vũ Hoàng Đế",
    "nienHieu": "không có[14]",
    "tenHuy": "Lý Phật Tử[15] (李佛子)",
    "theThu": "Người trong họ Lý Nam Đế[15]",
    "namTriVi": "555—602",
    "ten": "Hậu Lý Nam Đế[aa]"
  },
  {
    "paperURL": "/wiki/L%C3%BD_S%C6%B0_L%E1%BB%A3i",
    "mieuHieu": "không có[16]",
    "thuyHieu": "không có[16]",
    "nienHieu": "không có[16]",
    "tenHuy": "Lý Sư Lợi[16]",
    "theThu": "con Hậu Lý Nam Đế[16]",
    "namTriVi": "602—603",
    "ten": "Lý Sư Lợi[ad]"
  },
  {
    "paperURL": "/wiki/Mai_H%E1%BA%AFc_%C4%90%E1%BA%BF",
    "mieuHieu": "không có",
    "thuyHieu": "Đại Đế, Hắc Đế[ae]",
    "nienHieu": "không có",
    "tenHuy": "Mai Thúc Loan,[18] (梅叔鸞) Mai Huyền Thành,[19] Mai Lập Thành,[20] Mai Thúc Yên,[21] Mai Phượng.[af]",
    "theThu": "Con Mai Hoàn, sáng lập triều đại.",
    "namTriVi": "713—722",
    "ten": "Mai Hắc Đế[18]"
  },
  {
    "paperURL": "/wiki/Mai_Thi%E1%BA%BFu_%C4%90%E1%BA%BF",
    "mieuHieu": "không có",
    "thuyHieu": "không có",
    "nienHieu": "không có",
    "tenHuy": "Mai Thúc Huy, Mai Bảo Sơn",
    "theThu": "Con út Mai Hắc Đế, em song sinh với Bạch Đầu Đế.",
    "namTriVi": "722—723",
    "ten": "Mai Thiếu Đế[ah]"
  },
  {
    "paperURL": "/wiki/B%E1%BA%A1ch_%C4%90%E1%BA%A7u_%C4%90%E1%BA%BF",
    "mieuHieu": "không có",
    "thuyHieu": "không có",
    "nienHieu": "không có",
    "tenHuy": "Mai Kỳ Sơn",
    "theThu": "Con thứ hai Mai Hắc Đế, anh song sinh với Mai Thiếu Đế.",
    "namTriVi": "723—723",
    "ten": "Bạch Đầu Đế[ah]"
  },
  {
    "paperURL": "/wiki/Ph%C3%B9ng_H%C6%B0ng",
    "mieuHieu": "không có",
    "thuyHieu": "Bố Cái Đại Vương[aj]",
    "nienHieu": "không có",
    "tenHuy": "Phùng Hưng (馮興), Phùng Cự Lão",
    "theThu": "con Phùng Hạp Khanh, thế tập Biên Khố Di Tù Trưởng",
    "namTriVi": "766—791",
    "ten": "Phùng Hưng[ai]"
  },
  {
    "paperURL": "/wiki/Ph%C3%B9ng_An",
    "mieuHieu": "không có",
    "thuyHieu": "không có",
    "nienHieu": "không có",
    "tenHuy": "Phùng An",
    "theThu": "con Phùng Hưng",
    "namTriVi": "791—791",
    "ten": "Phùng An[al]"
  },
  {
    "paperURL": "/wiki/Kh%C3%BAc_Th%E1%BB%ABa_D%E1%BB%A5",
    "mieuHieu": "Tiên Chủ[an]",
    "thuyHieu": "Tiên Vương",
    "nienHieu": "không có",
    "tenHuy": "Khúc Thừa Dụ[22] (曲承裕)",
    "theThu": "Mở màn nền tự chủ[22]",
    "namTriVi": "905—907",
    "ten": "Khúc Tiên Chủ[am]"
  },
  {
    "paperURL": "/wiki/Kh%C3%BAc_H%E1%BA%A1o",
    "mieuHieu": "Trung Chủ[an]",
    "thuyHieu": "Trung Vương",
    "nienHieu": "không có",
    "tenHuy": "Khúc Hạo,[22] (曲顥) Khúc Thừa Hạo[23]",
    "theThu": "Con Khúc Thừa Dụ[22]",
    "namTriVi": "907—917",
    "ten": "Khúc Trung Chủ[am]"
  },
  {
    "paperURL": "/wiki/Kh%C3%BAc_Th%E1%BB%ABa_M%E1%BB%B9",
    "mieuHieu": "Hậu Chủ[an]",
    "thuyHieu": "Hậu Vương",
    "nienHieu": "không có",
    "tenHuy": "Khúc Thừa Mỹ[23] (曲承美) Khúc Toàn Mỹ",
    "theThu": "Con Khúc Hạo[23]",
    "namTriVi": "917—923",
    "ten": "Khúc Hậu Chủ[am]"
  },
  {
    "paperURL": "/wiki/D%C6%B0%C6%A1ng_%C4%90%C3%ACnh_Ngh%E1%BB%87",
    "mieuHieu": "không có",
    "thuyHieu": "không có",
    "nienHieu": "không có",
    "tenHuy": "Dương Đình Nghệ,[22] (楊廷藝) Dương Diên Nghệ[25] (楊筵藝)",
    "theThu": "Khôi phục nền tự chủ; nha tướng của Khúc Hạo",
    "namTriVi": "931—937",
    "ten": "Dương Chính Công[am]"
  },
  {
    "paperURL": "/wiki/Ki%E1%BB%81u_C%C3%B4ng_Ti%E1%BB%85n",
    "mieuHieu": "không có",
    "thuyHieu": "không có",
    "nienHieu": "không có",
    "tenHuy": "Kiều Công Tiễn,[23] (矯公羨) Kiểu Công Tiễn,[22] Kiểu Công Hạo,[25]",
    "theThu": "Con nuôi và nha tướng của Dương Đình Nghệ",
    "namTriVi": "937—938",
    "ten": "Kiều Công Tiễn[am]"
  },
  {
    "mieuHieu": "",
    "thuyHieu": "",
    "nienHieu": "",
    "tenHuy": "",
    "theThu": "",
    "namTriVi": "\u0026nbsp;Minh thuộc\u0026nbsp;",
    "ten": ""
  },
  {
    "mieuHieu": "",
    "thuyHieu": "Nhà Đinh",
    "nienHieu": "Nhà Tiền Lê",
    "tenHuy": "Nhà Lý",
    "theThu": "Nhà Trần",
    "namTriVi": "Nhà HồNhà Hậu Trần\u0026nbsp;",
    "ten": "Nhà Ngô"
  },
  {
    "mieuHieu": "",
    "thuyHieu": "",
    "nienHieu": "",
    "tenHuy": "",
    "theThu": "",
    "namTriVi": "\u0026nbsp;\u0026nbsp;",
    "ten": ""
  },
  {
    "paperURL": "/wiki/Ti%E1%BB%81n_Ng%C3%B4_V%C6%B0%C6%A1ng",
    "mieuHieu": "Tiên Chủ",
    "thuyHieu": "không có",
    "nienHieu": "không có",
    "tenHuy": "Ngô Quyền[22]",
    "theThu": "Sáng lập triều đại; con rể Dương Đình Nghệ",
    "namTriVi": "939—944",
    "ten": "Tiền Ngô Vương"
  },
  {
    "paperURL": "/wiki/D%C6%B0%C6%A1ng_B%C3%ACnh_V%C6%B0%C6%A1ng",
    "mieuHieu": "không có",
    "thuyHieu": "Trương Dương Công[ap]",
    "nienHieu": "không có",
    "tenHuy": "Dương Tam Kha,[22] Dương Chủ Tướng,[26] Dương Thiệu Hồng[27]",
    "theThu": "Con trai Dương Đình Nghệ",
    "namTriVi": "944—950",
    "ten": "Dương Bình Vương[ao]"
  },
  {
    "paperURL": "/wiki/Thi%C3%AAn_S%C3%A1ch_V%C6%B0%C6%A1ng",
    "mieuHieu": "không có",
    "thuyHieu": "không có",
    "nienHieu": "không có",
    "tenHuy": "Ngô Xương Ngập[22]",
    "theThu": "Con trưởng Ngô Quyền",
    "namTriVi": "951—954",
    "ten": "Thiên Sách Vương[aq]"
  },
  {
    "paperURL": "/wiki/Nam_T%E1%BA%A5n_V%C6%B0%C6%A1ng",
    "mieuHieu": "không có",
    "thuyHieu": "không có",
    "nienHieu": "không có",
    "tenHuy": "Ngô Xương Tấn,[24] Ngô Xương Văn[22]",
    "theThu": "Con thứ Ngô Quyền",
    "namTriVi": "950—965",
    "ten": "Nam Tấn Vương[aq]"
  },
  {
    "paperURL": "/wiki/Ng%C3%B4_X%C6%B0%C6%A1ng_X%C3%AD",
    "mieuHieu": "không có",
    "thuyHieu": "không có",
    "nienHieu": "không có",
    "tenHuy": "Ngô Xương Xí[22]",
    "theThu": "Con Ngô Xương Ngập",
    "namTriVi": "965—966",
    "ten": "Ngô Sứ Quân[28]"
  },
  {
    "paperURL": "/wiki/%C4%90inh_Ti%C3%AAn_Ho%C3%A0ng",
    "mieuHieu": "không có",
    "thuyHieu": "Tiên Hoàng Đế[at] Đại Thắng Minh Hoàng Đế",
    "nienHieu": "Thái Bình (970-979)",
    "tenHuy": "Đinh Bộ Lĩnh,[29] Đinh Hoàn[au]",
    "theThu": "Sáng lập triều đại; con nuôi Sứ quân Trần Minh Công",
    "namTriVi": "968—979",
    "ten": "Đinh Tiên Hoàng[as]"
  },
  {
    "paperURL": "/wiki/%C4%90inh_Ph%E1%BA%BF_%C4%90%E1%BA%BF",
    "mieuHieu": "không có",
    "thuyHieu": "Phế Đế[aw] Thiếu Đế",
    "nienHieu": "Thái Bình[ax] (979-980)",
    "tenHuy": "Đinh Toàn,[29] Đinh Tuệ[30]",
    "theThu": "Con trai thứ 2 Đinh Tiên Hoàng",
    "namTriVi": "979—980",
    "ten": "Đinh Phế Đế[av]"
  },
  {
    "paperURL": "/wiki/L%C3%AA_%C4%90%E1%BA%A1i_H%C3%A0nh",
    "mieuHieu": "không có[az]",
    "thuyHieu": "Đại Hành Hoàng Đế[ba] Minh Càn Ứng Vận Thần Vũ Thăng Bình Chí Nhân Quảng Hiếu Hoàng đế",
    "nienHieu": "Thiên Phúc (980–988) Hưng Thống (989–993) Ứng Thiên (994–1005)",
    "tenHuy": "Lê Hoàn[31]",
    "theThu": "Sáng lập triều đại, Phó vương nhiếp chính thời Đinh Phế Đế",
    "namTriVi": "980—1005",
    "ten": "Lê Đại Hành[ay]"
  },
  {
    "paperURL": "/wiki/L%C3%AA_Trung_T%C3%B4ng_(Ti%E1%BB%81n_L%C3%AA)",
    "mieuHieu": "Trung Tông",
    "thuyHieu": "không có",
    "nienHieu": "Ứng Thiên[ax] (1005–1005)",
    "tenHuy": "Lê Long Việt[31]",
    "theThu": "Con thứ Lê Đại Hành",
    "namTriVi": "1005—1005",
    "ten": "Lê Trung Tông"
  },
  {
    "paperURL": "/wiki/L%C3%AA_Long_%C4%90%C4%A9nh",
    "mieuHieu": "không có[bb]",
    "thuyHieu": "Khai Thiên Ứng Vận Thánh Văn Thần Vũ Tắc Thiên Sùng Đạo Đại Thắng Minh Quang Hiếu Hoàng Đế Ngọa Triều Hoàng Đế[bc]",
    "nienHieu": "Ứng Thiên[ax] (1005–1007) Cảnh Thụy (1008–1009)",
    "tenHuy": "Lê Long Đĩnh,[29]",
    "theThu": "Con thứ năm Lê Đại Hành",
    "namTriVi": "1005—1009",
    "ten": "Lê Ngọa Triều"
  },
  {
    "paperURL": "/wiki/L%C3%BD_Th%C3%A1i_T%E1%BB%95",
    "mieuHieu": "Thái Tổ[32]",
    "thuyHieu": "Thần Vũ Hoàng Đế[32]",
    "nienHieu": "Thuận Thiên (1010–1028)[32]",
    "tenHuy": "Lý Công Uẩn[32]",
    "theThu": "Sáng lập triều đại. Nguyên là Điện tiền Chỉ huy sứ và là Phò mã trưởng Lê Đại Hành[32]",
    "namTriVi": "1009—1028",
    "ten": "Lý Thái Tổ[bd]"
  },
  {
    "paperURL": "/wiki/L%C3%BD_Th%C3%A1i_T%C3%B4ng",
    "mieuHieu": "Thái Tông[32]",
    "thuyHieu": "Từ Hiếu Hoàng đế[bf]",
    "nienHieu": "Thiên Thành (1028–1033),[32] Thông Thụy (1034–1038),[32] Càn Phù Hữu Đạo (1039–1041),[32] Minh Đạo (1042–1043),[32] Thiên Cảm Thánh Vũ (1044–1048),[32] Sùng Hưng Đại Bảo (1049–1054).[32]",
    "tenHuy": "Lý Phật Mã,[32] Lý Đức Chính[32]",
    "theThu": "Con trưởng Lý Thái Tổ[32]",
    "namTriVi": "1028—1054",
    "ten": "Lý Thái Tông[be]"
  },
  {
    "paperURL": "/wiki/L%C3%BD_Th%C3%A1nh_T%C3%B4ng",
    "mieuHieu": "Thánh Tông",
    "thuyHieu": "Thánh Thần Hoàng đế[bg][33]",
    "nienHieu": "Long Thụy Thái Bình (1054–1058),[33] Chương Thánh Gia Khánh (1059–1065),[33] Long Chương Thiên Tự (1066–1068),[33] Thiên Huống Bảo Tượng (1068–1069),[33] Thần Vũ (1069–1072).[33]",
    "tenHuy": "Lý Nhật Tôn[33]",
    "theThu": "Con trưởng Lý Thái Tông[33]",
    "namTriVi": "1054—1072",
    "ten": "Lý Thánh Tông"
  },
  {
    "paperURL": "/wiki/L%C3%BD_Nh%C3%A2n_T%C3%B4ng",
    "mieuHieu": "Nhân Tông",
    "thuyHieu": "Hiếu Từ Thánh Thần Văn Vũ Hoàng Đế[33]",
    "nienHieu": "Thái Ninh (1072–1076),[34] Anh Vũ Chiêu Thắng (1076–1084),[34] Quảng Hựu (1085–1092),[34] Hội Phong (1092–1100),[35] Long Phù (1101–1109),[35] Hội Tường Đại Khánh (1110–1119),[35] Thiên Phù Duệ Vũ (1120–1126),[35] Thiên Phù Khánh Thọ (1127).[35]",
    "tenHuy": "Lý Càn Đức[33]",
    "theThu": "Con trưởng Lý Thánh Tông[33]",
    "namTriVi": "1072—1127",
    "ten": "Lý Nhân Tông[bh]"
  },
  {
    "paperURL": "/wiki/L%C3%BD_Th%E1%BA%A7n_T%C3%B4ng",
    "mieuHieu": "Thần Tông",
    "thuyHieu": "Quảng Văn Sùng Hiếu Khâm Minh Văn Vũ Hoàng Đế[33]",
    "nienHieu": "Thiên Thuận (1128–1132),[35] Thiên Chương Bảo Tự (1133–1138)[35]",
    "tenHuy": "Lý Dương Hoán[33]",
    "theThu": "con Sùng Hiền Hầu, cháu nội Lý Thánh Tông[33]",
    "namTriVi": "1127—1138",
    "ten": "Lý Thần Tông[bi]"
  },
  {
    "paperURL": "/wiki/L%C3%BD_Anh_T%C3%B4ng",
    "mieuHieu": "Anh Tông",
    "thuyHieu": "Chí Hiếu Hoàng Đế[bk][36]",
    "nienHieu": "Thiệu Minh (1138–1139),[35] Đại Định (1140–1162),[35] Chính Long Bảo Ứng (1163–1173),[37] Thiên Cảm Chí Bảo (1174–1175)[37]",
    "tenHuy": "Lý Thiên Tộ[36]",
    "theThu": "Con thứ Lý Thần Tông[36]",
    "namTriVi": "1138—1175",
    "ten": "Lý Anh Tông[bj]"
  },
  {
    "paperURL": "/wiki/L%C3%BD_Cao_T%C3%B4ng",
    "mieuHieu": "Cao Tông",
    "thuyHieu": "Quang Hiếu Hoàng Đế[36][bl]",
    "nienHieu": "Trinh Phù (1176–1185),[37] Thiên Tư Gia Thụy (1186–1201),[37] Thiên Gia Bảo Hựu (1202–1204),[37] Trị Bình Long Ứng (1205–1210)[37]",
    "tenHuy": "Lý Long Cán[38] Lý Long Trát[36]",
    "theThu": "Con thứ 6 Lý Anh Tông[36]",
    "namTriVi": "1176—1204",
    "ten": "Lý Cao Tông"
  },
  {
    "paperURL": "/wiki/L%C3%BD_Th%E1%BA%A9m",
    "mieuHieu": "không có[37]",
    "thuyHieu": "không có[37]",
    "nienHieu": "không có[37]",
    "tenHuy": "Lý Thẩm[37]",
    "theThu": "Con thứ Lý Cao Tông[37]",
    "namTriVi": "1209—1209",
    "ten": "Lý Thẩm[bm][bn]"
  },
  {
    "paperURL": "/wiki/L%C3%BD_Hu%E1%BB%87_T%C3%B4ng",
    "mieuHieu": "Huệ Tông",
    "thuyHieu": "Hoành Hiếu Hoàng đế[36][bp]",
    "nienHieu": "Kiến Gia (1211–1224)[37]",
    "tenHuy": "Lý Sảm,[36] Lý Hạo Sảm[37]",
    "theThu": "Con trưởng Lý Cao Tông[37]",
    "namTriVi": "1211—1224",
    "ten": "Lý Huệ Tông[bo]"
  },
  {
    "paperURL": "/wiki/L%C3%BD_Nguy%C3%AAn_V%C6%B0%C6%A1ng",
    "mieuHieu": "không có",
    "thuyHieu": "Nguyên Vương[br] Văn Vương",
    "nienHieu": "Càn Ninh (1214–1216)[39]",
    "tenHuy": "không rõ[39]",
    "theThu": "Con thứ Lý Anh Tông[39]",
    "namTriVi": "1214—1216",
    "ten": "Lý Nguyên Vương[bn][bq]"
  },
  {
    "paperURL": "/wiki/L%C3%BD_Chi%C3%AAu_Ho%C3%A0ng",
    "mieuHieu": "không có[39]",
    "thuyHieu": "Chiêu Hoàng[bt]",
    "nienHieu": "Thiên Chương Hữu Đạo (1224–1225)[39]",
    "tenHuy": "Lý Phật Kim,[36] Lý Thiên Hinh[39]",
    "theThu": "Con gái Lý Huệ Tông, vợ Trần Thái Tông[39]",
    "namTriVi": "1224—1225",
    "ten": "Lý Chiêu Hoàng[bs]"
  },
  {
    "paperURL": "/wiki/Tr%E1%BA%A7n_Th%C3%A1i_T%C3%B4ng",
    "mieuHieu": "Thái Tông[40] Thiện Hoàng Văn Hoàng",
    "thuyHieu": "Thống Thiên Ngự Cực Long Công Hậu Đức Hiền Công Hựu Thuận Thánh Văn Thần Vũ Hiếu Nguyên Hoàng Đế[40]",
    "nienHieu": "Kiến Trung (1225–1232)[40] Thiên Ứng Chính Bình (1232–1351)[40] Nguyên Phong (1251–1258)[40]",
    "tenHuy": "Trần Cảnh[40] Trần Bồ[40] Trần Quang Bỉnh[41] Trần Nhật Cảnh[42]",
    "theThu": "Sáng lập triều đại, chồng và anh họ Lý Chiêu Hoàng[40]",
    "namTriVi": "1225—1258",
    "ten": "Trần Thái Tông[bu]"
  },
  {
    "paperURL": "/wiki/Tr%E1%BA%A7n_Th%C3%A1nh_T%C3%B4ng",
    "mieuHieu": "Thánh Tông[40] Nhân Hoàng",
    "thuyHieu": "Huyền Công Thịnh Đức Nhân Minh Văn Vũ Tuyên Hiếu Hoàng Đế[40]",
    "nienHieu": "Thiệu Long (1258–1272)[40] Bảo Phù (1273–1278)[40]",
    "tenHuy": "Trần Hoảng[40] Trần Uy Hoảng[42] Trần Quang Bính[41] Trần Nhật Huyên[41]",
    "theThu": "Con thứ hai Trần Thái Tông[40]",
    "namTriVi": "1258—1279",
    "ten": "Trần Thánh Tông[bv]"
  },
  {
    "paperURL": "/wiki/Tr%E1%BA%A7n_Nh%C3%A2n_T%C3%B4ng",
    "mieuHieu": "Nhân Tông[43] Hiếu Hoàng",
    "thuyHieu": "Pháp Thiên Sùng Đạo Ứng Thế Hóa Dân Long Từ Hiển Hiệu Thánh Văn Thần Vũ Nguyên Minh Duệ Hiếu Hoàng Đế[43]",
    "nienHieu": "Thiệu Bảo (1278–1285)[43] Trùng Hưng (1285–1293)[43]",
    "tenHuy": "Trần Khâm[43] Trần Nhật Tuấn[41]",
    "theThu": "Con trưởng Trần Thánh Tông[43]",
    "namTriVi": "1278—1293",
    "ten": "Trần Nhân Tông[bw]"
  },
  {
    "paperURL": "/wiki/Tr%E1%BA%A7n_Anh_T%C3%B4ng",
    "mieuHieu": "Anh Tông[43] Anh Hoàng",
    "thuyHieu": "Hiển Văn Duệ Vũ Khâm Minh Nhân Hiếu Hoàng Đế[43]",
    "nienHieu": "Hưng Long (1293–1314)[43]",
    "tenHuy": "Trần Thuyên[43] Trần Nhật 㷃[41] Trần Nhật 𤊞[42]",
    "theThu": "Con trưởng Trần Nhân Tông",
    "namTriVi": "1293—1314",
    "ten": "Trần Anh Tông[bx]"
  },
  {
    "paperURL": "/wiki/Tr%E1%BA%A7n_Minh_T%C3%B4ng",
    "mieuHieu": "Minh Tông[44] Ninh Hoàng",
    "thuyHieu": "Chương Nghiêu Văn Triết Hoàng Đế[44]",
    "nienHieu": "Đại Khánh (1314–1323)[44] Khai Thái (1324–1329)[44]",
    "tenHuy": "Trần Mạnh[44] Trần Thánh Sinh[bz] Trần Nhật Khoáng[41]",
    "theThu": "Con thứ tư Trần Anh Tông[44]",
    "namTriVi": "1314—1329",
    "ten": "Trần Minh Tông[by]"
  },
  {
    "paperURL": "/wiki/Tr%E1%BA%A7n_Hi%E1%BA%BFn_T%C3%B4ng",
    "mieuHieu": "Hiến Tông[44] Triết Hoàng",
    "thuyHieu": "[44] Thể Nguyên Ngự Cực Duệ Thánh Chí Hiếu Hoàng Đế",
    "nienHieu": "Khai Hựu (1329–1341)[44]",
    "tenHuy": "Trần Vượng[44] Trần Thiên Kiến [44] Trần Nhật 㷆[41]",
    "theThu": "Con trưởng Trần Minh Tông[44]",
    "namTriVi": "1329—1341",
    "ten": "Trần Hiến Tông[ca]"
  },
  {
    "paperURL": "/wiki/Tr%E1%BA%A7n_D%E1%BB%A5_T%C3%B4ng",
    "mieuHieu": "Dụ Tông[44] Dụ Hoàng",
    "thuyHieu": "Thống Thiên Thể Đạo Nhân Minh Quang Hiếu Hoàng đế[44]",
    "nienHieu": "Thiệu Phong (1341–1357)[44] Đại Trị (1358–1369)[44]",
    "tenHuy": "Trần Hạo[44] Trần Nhật Khuê[45]",
    "theThu": "Con thứ mười Trần Minh Tông, dòng hoàng đích tử[44]",
    "namTriVi": "1341—1369",
    "ten": "Trần Dụ Tông[cb]"
  },
  {
    "paperURL": "/wiki/Tr%E1%BA%A7n_Nh%E1%BA%ADt_L%E1%BB%85",
    "mieuHieu": "không có[44]",
    "thuyHieu": "Hôn Đức Công[cd]",
    "nienHieu": "Đại Định (1369–1370)[44]",
    "tenHuy": "Trần Nhật Lễ[44] Dương Nhật Lễ[44] Trần Nhật Kiên[45]",
    "theThu": "Con riêng của chị dâu Trần Dụ Tông[44]",
    "namTriVi": "1369—1370",
    "ten": "Đại Định Đế[cc]"
  },
  {
    "paperURL": "/wiki/Tr%E1%BA%A7n_Ngh%E1%BB%87_T%C3%B4ng",
    "mieuHieu": "Nghệ Tông[46] Nghệ Hoàng Nghĩa Hoàng",
    "thuyHieu": "Quang Nhiên Anh Triết Hoàng Đế[46] Thể Thiên Kiến Cực Thuần Hiếu Hoàng Đế",
    "nienHieu": "Thiệu Khánh (1370–1372)[44]",
    "tenHuy": "Trần Phủ[46] Trần Thúc Minh[45]",
    "theThu": "Con thứ ba Trần Minh Tông",
    "namTriVi": "1370—1372",
    "ten": "Trần Nghệ Tông[ce]"
  },
  {
    "paperURL": "/wiki/Tr%E1%BA%A7n_Du%E1%BB%87_T%C3%B4ng",
    "mieuHieu": "Duệ Tông[44] Khâm Hoàng",
    "thuyHieu": "Kế Thiên Ứng Vận Nhân Minh Khâm Hiếu Hoàng Đế",
    "nienHieu": "Long Khánh (1373–1377)[44]",
    "tenHuy": "Trần Kính[44] Trần Nhật Đoan[45]",
    "theThu": "Con thứ 11 Trần Minh Tông[44]",
    "namTriVi": "1372—1377",
    "ten": "Trần Duệ Tông[cf]"
  },
  {
    "paperURL": "/wiki/Tr%E1%BA%A7n_Ph%E1%BA%BF_%C4%90%E1%BA%BF_(%C4%90%E1%BA%A1i_Vi%E1%BB%87t)",
    "mieuHieu": "Giản Hoàng[46]",
    "thuyHieu": "Phế Đế[aw]",
    "nienHieu": "Xương Phù (1377–1388)[46]",
    "tenHuy": "Trần Hiện[46] Trần Nhật Vĩ[45]",
    "theThu": "Con thứ Trần Duệ Tông[46]",
    "namTriVi": "1377—1388",
    "ten": "Trần Phế Đế[cg]"
  },
  {
    "paperURL": "/wiki/Tr%E1%BA%A7n_Thu%E1%BA%ADn_T%C3%B4ng",
    "mieuHieu": "Thuận Tông[46] Nguyên Hoàng",
    "thuyHieu": "không có[46]",
    "nienHieu": "Quang Thái (1388–1398)[46]",
    "tenHuy": "Trần Ngung[46] Trần Nhật Hỗn[45]",
    "theThu": "Con thứ của Trần Nghệ Tông[46]",
    "namTriVi": "1388—1398",
    "ten": "Trần Thuận Tông[ch]"
  },
  {
    "paperURL": "/wiki/Tr%E1%BA%A7n_Thi%E1%BA%BFu_%C4%90%E1%BA%BF",
    "mieuHieu": "không có[46]",
    "thuyHieu": "Thiếu Đế[ci]",
    "nienHieu": "Kiến Tân (1398–1400)[46]",
    "tenHuy": "Trần An[46]",
    "theThu": "Con trưởng Trần Thuận Tông, cháu ngoại Hồ Quý Ly[46]",
    "namTriVi": "1398—1400",
    "ten": "Trần Thiếu Đế[46]"
  },
  {
    "paperURL": "/wiki/H%E1%BB%93_Qu%C3%BD_Ly",
    "mieuHieu": "Quốc Tổ",
    "thuyHieu": "Chương Hoàng",
    "nienHieu": "Thánh Nguyên (1400)",
    "tenHuy": "Hồ Quý Ly Hồ Nhất Nguyên Lê Quý Ly Lê Nhất Nguyên",
    "theThu": "Sáng lập triều đại, phò mã Trần Minh Tông, ông ngoại Trần Thiếu Đế",
    "namTriVi": "1400—1400",
    "ten": "Hồ Quý Ly[cj]"
  },
  {
    "paperURL": "/wiki/H%E1%BB%93_H%C3%A1n_Th%C6%B0%C6%A1ng",
    "mieuHieu": "không có[46]",
    "thuyHieu": "không có[46]",
    "nienHieu": "Thiệu Thành (1401–1402) Khai Đại (1403–1407)",
    "tenHuy": "Hồ Hán Thương[46] Lê Hán Thương[46] Hồ Hỏa[45]",
    "theThu": "Con thứ Hồ Quý Ly",
    "namTriVi": "1400—1407",
    "ten": "Hồ Hán Thương"
  },
  {
    "paperURL": "/wiki/Tr%E1%BA%A7n_Nguy%E1%BB%87t_H%E1%BB%93",
    "mieuHieu": "không có",
    "thuyHieu": "không có",
    "nienHieu": "không có",
    "tenHuy": "Trần Nguyệt Hồ",
    "theThu": "không rõ",
    "namTriVi": "1407—1407",
    "ten": "Trần Nguyệt Hồ"
  },
  {
    "paperURL": "/wiki/Gi%E1%BA%A3n_%C4%90%E1%BB%8Bnh_%C4%90%E1%BA%BF",
    "mieuHieu": "không có",
    "thuyHieu": "không có[ck]",
    "nienHieu": "Hưng Khánh (1407–1409)",
    "tenHuy": "Trần Ngỗi, Trần Quỹ",
    "theThu": "Con trai thứ Trần Nghệ Tông",
    "namTriVi": "1407—1409",
    "ten": "Giản Định Đế"
  },
  {
    "paperURL": "/wiki/Tr%C3%B9ng_Quang_%C4%90%E1%BA%BF",
    "mieuHieu": "không có",
    "thuyHieu": "không có",
    "nienHieu": "Trùng Quang (1409–1414)",
    "tenHuy": "Trần Quý Khoáng, Trần Quý Khoách",
    "theThu": "Cháu nội Trần Nghệ Tông",
    "namTriVi": "1409—1414",
    "ten": "Trùng Quang Đế"
  },
  {
    "paperURL": "/wiki/L%C3%AA_Th%C3%A1i_T%E1%BB%95",
    "mieuHieu": "Thái Tổ[48] Lam Sơn động chủ",
    "thuyHieu": "Thống Thiên Khải Vận Thánh Đức Thần Công Duệ Văn Anh Vũ Khoan Minh Dũng Trí Hoàng Nghĩa Chí Minh Đại Hiếu Cao Hoàng Đế[48]",
    "nienHieu": "Thuận Thiên (1428–1433)[48]",
    "tenHuy": "Lê Lợi[48]",
    "theThu": "Sáng lập triểu đại[48]",
    "namTriVi": "1428–1433",
    "ten": "Lê Thái Tổ[cn]"
  },
  {
    "paperURL": "/wiki/L%C3%AA_Th%C3%A1i_T%C3%B4ng",
    "mieuHieu": "Thái Tông[50] Quế Lâm động chủ",
    "thuyHieu": "Kế Thiên Thể Đạo Hiển Đức Thánh Công Khâm Minh Văn Tư Anh Duệ Triết Chiêu Hiến Kiến Trung Văn Hoàng Đế[50]",
    "nienHieu": "Thiệu Bình (1434–1439)[50] Đại Bảo (1440-1442)[50]",
    "tenHuy": "Lê Nguyên Long[50] Lê Lân[45]",
    "theThu": "Con thứ hai Lê Thái Tổ[50]",
    "namTriVi": "1433–1442",
    "ten": "Lê Thái Tông[co]"
  },
  {
    "paperURL": "/wiki/L%C3%AA_Nh%C3%A2n_T%C3%B4ng",
    "mieuHieu": "Nhân Tông[50]",
    "thuyHieu": "Khâm Văn Nhân Hiếu Tuyên Minh Thông Duệ Tuyên Hoàng Đế[51]",
    "nienHieu": "Thái Hòa (1443–1453)[50] Diên Ninh (1454–1459)[50]",
    "tenHuy": "Lê Bang Cơ[50] Lê Cơ Long Lê Tuấn[52]",
    "theThu": "Con thứ ba Lê Thái Tông[50]",
    "namTriVi": "1442–1459",
    "ten": "Lê Nhân Tông"
  },
  {
    "paperURL": "/wiki/L%C3%AA_Nghi_D%C3%A2n",
    "mieuHieu": "không có[50]",
    "thuyHieu": "Lệ Đức Hầu[cq]",
    "nienHieu": "Thiên Hưng (1459–1460)[50]",
    "tenHuy": "Lê Nghi Dân[50] Lê Tông[52]",
    "theThu": "Con trưởng Lê Thái Tông[50]",
    "namTriVi": "1459–1460",
    "ten": "Lạng Sơn Vương[cp]"
  },
  {
    "paperURL": "/wiki/L%C3%AA_Th%C3%A1nh_T%C3%B4ng",
    "mieuHieu": "Thánh Tông[51] Thiên Nam động chủ",
    "thuyHieu": "Sùng Thiên Quảng Vận Cao Minh Quang Chính Chí Đức Đại Công Thánh Văn Thần Vũ Đạt Hiếu Thuần Hoàng Đế[53]",
    "nienHieu": "Quang Thuận (1460–1469)[51] Hồng Đức (1470–1497)[51]",
    "tenHuy": "Lê Tư Thành[51] Lê Hạo[45]",
    "theThu": "Con thứ tư Lê Thái Tông[51]",
    "namTriVi": "1460–1497",
    "ten": "Lê Thánh Tông[cr]"
  },
  {
    "paperURL": "/wiki/L%C3%AA_Hi%E1%BA%BFn_T%C3%B4ng",
    "mieuHieu": "Hiến Tông[53] Thượng Dương động chủ",
    "thuyHieu": "Thể Thiên Ngưng Đạo Mậu Đức Chí Chiêu Văn Thiệu Vũ Tuyên Triết Khâm Thành Chương Hiếu Duệ Hoàng Đế[53]",
    "nienHieu": "Cảnh Thống (1497–1504)[53]",
    "tenHuy": "Lê Tranh[53] Lê Sanh[53] Lê Huy[53] Lê Tăng[45]",
    "theThu": "Con trưởng Lê Thánh Tông",
    "namTriVi": "1497–1504",
    "ten": "Lê Hiến Tông[cs]"
  },
  {
    "paperURL": "/wiki/L%C3%AA_T%C3%BAc_T%C3%B4ng",
    "mieuHieu": "Túc Tông[53] Tự Hoàng",
    "thuyHieu": "Chiêu Nghĩa Hiển Nhân Ôn Cung Uyên Mặc Hiếu Doãn Cung Khâm Hoàng Đế[53]",
    "nienHieu": "Thái Trinh (1504)[53]",
    "tenHuy": "Lê Thuần[53]",
    "theThu": "Con thứ ba Lê Hiến Tông",
    "namTriVi": "1504–1504",
    "ten": "Lê Túc Tông[ct]"
  },
  {
    "paperURL": "/wiki/L%C3%AA_Uy_M%E1%BB%A5c",
    "mieuHieu": "Quỳnh Đô động chủ[54]",
    "thuyHieu": "Uy Mục Đế[54]",
    "nienHieu": "Đoan Khánh (1505–1509)[53]",
    "tenHuy": "Lê Tuấn[53] Lê Huyên[53]",
    "theThu": "Con thứ hai Lê Hiến Tông[53]",
    "namTriVi": "1504–1509",
    "ten": "Lê Uy Mục[cu]"
  },
  {
    "paperURL": "/wiki/L%C3%AA_T%C6%B0%C6%A1ng_D%E1%BB%B1c",
    "mieuHieu": "Nhân Hải động chủ[54]",
    "thuyHieu": "Tương Dực Đế[54]",
    "nienHieu": "Hồng Thuận (1510–1516)[54]",
    "tenHuy": "Lê Oánh[55] Lê Oanh[55] Lê Dinh[54] Lê Trừu[54]",
    "theThu": "Con Lê Đức Tông, cháu nội Lê Thánh Tông[54]",
    "namTriVi": "1509–1516",
    "ten": "Lê Tương Dực[cv]"
  },
  {
    "paperURL": "/wiki/L%C3%AA_Quang_Tr%E1%BB%8B",
    "mieuHieu": "không có[54]",
    "thuyHieu": "không có[54]",
    "nienHieu": "không có[54]",
    "tenHuy": "Lê Quang Trị[54]",
    "theThu": "Con Lê Doanh, cháu nội Lê Đức Tông, cháu gọi Lê Tương Dực bằng bác[54]",
    "namTriVi": "1516–1516",
    "ten": "Lê Quang Trị[cw][cx]"
  },
  {
    "paperURL": "/wiki/L%C3%AA_Chi%C3%AAu_T%C3%B4ng",
    "mieuHieu": "Chiêu Tông[54]",
    "thuyHieu": "Thần Hoàng Đế[54]",
    "nienHieu": "Quang Thiệu (1516-1525)[54]",
    "tenHuy": "Lê Y[54] Lê Huệ[54]",
    "theThu": "Anh họ Lê Quang Trị, chắt Lê Thánh Tông[54]",
    "namTriVi": "1516–1525",
    "ten": "Lê Chiêu Tông[cy]"
  },
  {
    "paperURL": "/wiki/L%C3%AA_B%E1%BA%A3ng",
    "mieuHieu": "không có[54]",
    "thuyHieu": "không có[54]",
    "nienHieu": "Đại Đức (1518–1519)[54]",
    "tenHuy": "Lê Bảng[54]",
    "theThu": "Con Lê Lộc, Lộc là cháu nội Lê Khắc Xương, Khắc Xương là anh của Lê Thánh Tông[54]",
    "namTriVi": "1518–1519",
    "ten": "Lê Bảng[cx][cz]"
  },
  {
    "paperURL": "/wiki/L%C3%AA_Do",
    "mieuHieu": "không có[54]",
    "thuyHieu": "không có[54]",
    "nienHieu": "Thiên Hiến (1519)[54]",
    "tenHuy": "Lê Do[54] Lê Dữu[56]",
    "theThu": "Em cùng mẹ với Lê Bảng[54]",
    "namTriVi": "1519–1519",
    "ten": "Lê Do[cx][da]"
  },
  {
    "paperURL": "/wiki/L%C3%AA_Cung_Ho%C3%A0ng",
    "mieuHieu": "không có[54]",
    "thuyHieu": "Cung Hoàng Đế[54]",
    "nienHieu": "Thống Nguyên (1522–1527)[54]",
    "tenHuy": "Lê Xuân[54] Lê Lự[54] Lê Khánh[57]",
    "theThu": "Em Lê Chiêu Tông[54]",
    "namTriVi": "1522–1527",
    "ten": "Lê Cung Hoàng[db]"
  },
  {
    "paperURL": "/wiki/M%E1%BA%A1c_%C4%90%C4%83ng_Dung",
    "mieuHieu": "Thái Tổ[54]",
    "thuyHieu": "Nhân Minh Cao Hoàng Đế[58]",
    "nienHieu": "Minh Đức (1527–1530)[54]",
    "tenHuy": "Mạc Đăng Dung[54]",
    "theThu": "Cháu 7 đời Mạc Đĩnh Chi, sáng lập triều đại[58]",
    "namTriVi": "1527–1530",
    "ten": "Mạc Thái Tổ[dd]"
  },
  {
    "paperURL": "/wiki/M%E1%BA%A1c_Th%C3%A1i_T%C3%B4ng",
    "mieuHieu": "Thái Tông[54]",
    "thuyHieu": "Khâm Triết Văn Hoàng Đế[59]",
    "nienHieu": "Đại Chính (1530–1540)[59]",
    "tenHuy": "Mạc Đăng Doanh[59] Mạc Phương Doanh[45]",
    "theThu": "Con trưởng Mạc Thái Tổ[59]",
    "namTriVi": "1530–1540",
    "ten": "Mạc Thái Tông[de]"
  },
  {
    "paperURL": "/wiki/M%E1%BA%A1c_Hi%E1%BA%BFn_T%C3%B4ng",
    "mieuHieu": "Hiến Tông[60]",
    "thuyHieu": "Hiển Hoàng Đế[60]",
    "nienHieu": "Quảng Hòa (1540–1546)[60]",
    "tenHuy": "Mạc Phúc Hải[60] Mạc Đức Nguyên[60]",
    "theThu": "Con trưởng Mạc Thái Tông[60]",
    "namTriVi": "1540–1546",
    "ten": "Mạc Hiến Tông"
  },
  {
    "paperURL": "/wiki/M%E1%BA%A1c_Ch%C3%ADnh_Trung",
    "mieuHieu": "không có[61]",
    "thuyHieu": "không có[61]",
    "nienHieu": "không có[61]",
    "tenHuy": "Mạc Chính Trung[61]",
    "theThu": "Em Mạc Thái Tông[61]",
    "namTriVi": "1546–1547",
    "ten": "Mạc Chính Trung[df]"
  },
  {
    "paperURL": "/wiki/M%E1%BA%A1c_Tuy%C3%AAn_T%C3%B4ng",
    "mieuHieu": "Tuyên Tông[62]",
    "thuyHieu": "Anh Nghị Hoàng Đế Duệ Hoàng Đế[62]",
    "nienHieu": "Vĩnh Định (1547)[62] Cảnh Lịch (1548–1553)[62] Quang Bảo (1554–1561)[62]",
    "tenHuy": "Mạc Phúc Nguyên[62]",
    "theThu": "Con Mạc Hiến Tông[62]",
    "namTriVi": "1546–1561",
    "ten": "Mạc Tuyên Tông"
  },
  {
    "paperURL": "/wiki/M%E1%BA%A1c_M%E1%BA%ADu_H%E1%BB%A3p",
    "mieuHieu": "Mục Tông[63] Anh Tổ[64]",
    "thuyHieu": "An Thiên Huy Địa Trang Văn Cẩn Vũ Bình Định Huệ Cương Hiếu Tĩnh Hoàng Đế[64]",
    "nienHieu": "Thuần Phúc (1562–1565)[65] Sùng Khang (1566–1577)[65] Diên Thành (1578–1585)[65] Đoan Thái (1586–1587)[65] Hưng Trị (1588–1590)[65] Hồng Ninh (1591–1592)[65]",
    "tenHuy": "Mạc Mậu Hợp[65]",
    "theThu": "Con trai Mạc Tuyên Tông[65]",
    "namTriVi": "1561–1592",
    "ten": "Mạc Mục Tông Mạc Anh Tổ"
  },
  {
    "paperURL": "/wiki/M%E1%BA%A1c_To%C3%A0n",
    "mieuHieu": "Cảnh Tông[64]",
    "thuyHieu": "Khai Thiên Xung Địa An Văn Đoạt Vũ Thành Hoàng Đế[64]",
    "nienHieu": "Vũ An (1592–1592)[66]",
    "tenHuy": "Mạc Toàn[66]",
    "theThu": "Con thứ Mạc Mậu Hợp[66]",
    "namTriVi": "1592–1592",
    "ten": "Mạc Cảnh Tông"
  },
  {
    "paperURL": "/wiki/M%E1%BA%A1c_K%C3%ADnh_Ch%E1%BB%89",
    "mieuHieu": "Mẫn Tông[64]",
    "thuyHieu": "Hoài Nghị Minh Huấn Trinh Hoàng Đế[64]",
    "nienHieu": "Bảo Định (1592–1593)[66] Khang Hựu (1593–1593)[66]",
    "tenHuy": "Mạc Kính Chỉ[66] Mạc Kính Bang[45]",
    "theThu": "Con trưởng Mạc Kính Điển, cháu nội Mạc Thái Tông[66]",
    "namTriVi": "1592–1593",
    "ten": "Mạc Mẫn Tông[dg]"
  },
  {
    "paperURL": "/wiki/M%E1%BA%A1c_%C4%90%E1%BA%A1i_T%C3%B4ng",
    "mieuHieu": "Đại Tông[64]",
    "thuyHieu": "Khởi Thiên Đĩnh Địa Khắc Văn Định Vũ Linh Hoàng Đế[64]",
    "nienHieu": "Càn Thống (1593–1625)[67]",
    "tenHuy": "Mạc Kính Cung[67]",
    "theThu": "Con thứ 7 Mạc Kính Điển[67]",
    "namTriVi": "1592–1625",
    "ten": "Mạc Đại Tông[dh]"
  },
  {
    "paperURL": "/wiki/M%E1%BA%A1c_K%C3%ADnh_Khoan",
    "mieuHieu": "Quang Tổ[64]",
    "thuyHieu": "Hoà Thiên Phù Địa Độ Văn Khánh Vũ Huệ Nguyên Hoàng Đế[64]",
    "nienHieu": "Long Thái (1623–1638)[67]",
    "tenHuy": "Mạc Kính Khoan[67]",
    "theThu": "Cháu nội Mạc Kính Điển[67]",
    "namTriVi": "1623–1638",
    "ten": "Mạc Quang Tổ"
  },
  {
    "paperURL": "/wiki/M%E1%BA%A1c_K%C3%ADnh_V%C5%A9",
    "mieuHieu": "Minh Tông[64]",
    "thuyHieu": "Trang Thiên Huệ Địa Cảnh Văn Di Vũ Khai Hoàng Đế[64]",
    "nienHieu": "Thuận Đức (1638–1677)[68]",
    "tenHuy": "Mạc Kính Vũ Mạc Kính Hoàn Mạc Kính Diệu[69]",
    "theThu": "Con Mạc Kính Khoan[68]",
    "namTriVi": "1638–1677",
    "ten": "Mạc Minh Tông"
  },
  {
    "paperURL": "/wiki/M%E1%BA%A1c_K%C3%ADnh_H%E1%BA%BB",
    "mieuHieu": "Quý Tông[64]",
    "thuyHieu": "Hoàn Thiên Thanh Địa Đoạt Văn Dương Vũ Huệ Đại Vương[64]",
    "nienHieu": "Vĩnh Xương (1677–1681)[69]",
    "tenHuy": "Mạc Kính Hẻ[70] Mạc Kính Thụy[71] Mạc Nguyên Thanh[di]",
    "theThu": "Con Mạc Kính Vũ[70]",
    "namTriVi": "1677–1681",
    "ten": "Mạc Quý Tông"
  },
  {
    "paperURL": "/wiki/M%E1%BA%A1c_K%C3%ADnh_Quang",
    "mieuHieu": "Đức Tông[64]",
    "thuyHieu": "Thiên Địa Đại Bảo Văn Vũ Độ Đại Vương[64]",
    "nienHieu": "không có",
    "tenHuy": "Mạc Kính Quang[71] Mạc Kính Tiêu[70] Mạc Kính Hoảng[69]",
    "theThu": "Con Mạc Kính Vũ, em Mạc Nguyên Thanh[71]",
    "namTriVi": "1681–1683",
    "ten": "Mạc Đức Tông"
  },
  {
    "paperURL": "/wiki/L%C3%AA_Trang_T%C3%B4ng",
    "mieuHieu": "Trang Tông[72]",
    "thuyHieu": "Dụ Hoàng Đế[72]",
    "nienHieu": "Nguyên Hòa (1533–1548)[72]",
    "tenHuy": "Lê Ninh[72] Lê Huyến[72] Lê Duy Ninh[45]",
    "theThu": "Được cho là con Lê Chiêu Tông[72][dn]",
    "namTriVi": "1533–1548",
    "ten": "Lê Trang Tông[dm]"
  },
  {
    "paperURL": "/wiki/L%C3%AA_Trung_T%C3%B4ng_(H%E1%BA%ADu_L%C3%AA)",
    "mieuHieu": "Trung Tông[72]",
    "thuyHieu": "Vũ Hoàng Đế[72]",
    "nienHieu": "Thuận Bình (1548–1556)[72]",
    "tenHuy": "Lê Huyên[72] Lê Duy Huyên[45]",
    "theThu": "Con Lê Trang Tông[72]",
    "namTriVi": "1548–1556",
    "ten": "Lê Trung Tông"
  },
  {
    "paperURL": "/wiki/L%C3%AA_Anh_T%C3%B4ng",
    "mieuHieu": "Anh Tông[72]",
    "thuyHieu": "Tuấn Hoàng Đế[72]",
    "nienHieu": "Thiên Hựu (1556-1557)[72] Chính trị (1558–1571)[72] Hồng Phúc (1572–1573)[72]",
    "tenHuy": "Lê Duy Bang[72]",
    "theThu": "Cháu 6 đời của Lê Trừ, anh Lê Thái Tổ[dp]",
    "namTriVi": "1556–1573",
    "ten": "Lê Anh Tông[do]"
  },
  {
    "paperURL": "/wiki/L%C3%AA_Th%E1%BA%BF_T%C3%B4ng",
    "mieuHieu": "Thế Tông[66]",
    "thuyHieu": "Nghị Hoàng Đế[66]",
    "nienHieu": "Gia Thái (1573–1577)[66] Quang Hưng (1578–1599)[66]",
    "tenHuy": "Lê Đàm[73] Lê Duy Đàm[66]",
    "theThu": "Con thứ năm Lê Anh Tông[66]",
    "namTriVi": "1573–1599",
    "ten": "Lê Thế Tông[dq]"
  },
  {
    "paperURL": "/wiki/L%C3%AA_K%C3%ADnh_T%C3%B4ng",
    "mieuHieu": "Kính Tông[74]",
    "thuyHieu": "Huệ Hoàng Đế[74] Giản Huy Đế[75]",
    "nienHieu": "Thận Đức (1600-1600)[74] Hoằng Định (1601-1619)[74]",
    "tenHuy": "Lê Duy Tân[74]",
    "theThu": "Con thứ Lê Thế Tông[74]",
    "namTriVi": "1599–1619",
    "ten": "Lê Kính Tông[dr]"
  },
  {
    "paperURL": "/wiki/L%C3%AA_Th%E1%BA%A7n_T%C3%B4ng",
    "mieuHieu": "Thần Tông[74]",
    "thuyHieu": "Uyên Hoàng Đế[74]",
    "nienHieu": "Vĩnh Tộ (1620––1628)[74] Đức Long (1629–1634)[74] Dương Hoà (1635–1643)[74]",
    "tenHuy": "Lê Duy Kỳ[74]",
    "theThu": "Con trưởng Lê Kính Tông[74]",
    "namTriVi": "1619–1643",
    "ten": "Lê Thần Tông[ds]"
  },
  {
    "paperURL": "/wiki/L%C3%AA_Ch%C3%A2n_T%C3%B4ng",
    "mieuHieu": "Chân Tông[74]",
    "thuyHieu": "Thuận Hoàng Đế[74]",
    "nienHieu": "Phúc Thái (1643–1649)[74]",
    "tenHuy": "Lê Duy Hựu[74] Lê Duy Đề[70]",
    "theThu": "Con trưởng Lê Thần Tông[74]",
    "namTriVi": "1643–1649",
    "ten": "Lê Chân Tông"
  },
  {
    "paperURL": "/wiki/L%C3%AA_Th%E1%BA%A7n_T%C3%B4ng",
    "mieuHieu": "Thần Tông[76]",
    "thuyHieu": "Uyên Hoàng Đế[76]",
    "nienHieu": "Khánh Đức (1649–1652)[76] Thịnh Đức (1653–1657)[76] Vĩnh Thọ (1658–1661)[76] Vạn Khánh (1662)[76]",
    "tenHuy": "Lê Duy Kỳ[76]",
    "theThu": "Làm vua lần 2[77]",
    "namTriVi": "1649–1662",
    "ten": "Lê Thần Tông[ds]"
  },
  {
    "paperURL": "/wiki/L%C3%AA_Huy%E1%BB%81n_T%C3%B4ng",
    "mieuHieu": "Huyền Tông[78]",
    "thuyHieu": "Mục Hoàng Đế[78]",
    "nienHieu": "Cảnh Trị (1663–1671)[78]",
    "tenHuy": "Lê Duy Vũ[78] Lê Duy Hy[70]",
    "theThu": "Con thứ Lê Thần Tông[78]",
    "namTriVi": "1663–1671",
    "ten": "Lê Huyền Tông[dt]"
  },
  {
    "paperURL": "/wiki/L%C3%AA_Gia_T%C3%B4ng",
    "mieuHieu": "Gia Tông[78]",
    "thuyHieu": "Mỹ Hoàng Đế[78]",
    "nienHieu": "Dương Đức (1672––1673)[78] Đức Nguyên (1674-1675)[78]",
    "tenHuy": "Lê Duy Cối[78] Lê Duy Khoái[79]",
    "theThu": "Con thứ Lê Thần Tông[78]",
    "namTriVi": "1671–1675",
    "ten": "Lê Gia Tông[du]"
  },
  {
    "paperURL": "/wiki/L%C3%AA_Hy_T%C3%B4ng",
    "mieuHieu": "Hy Tông[80]",
    "thuyHieu": "Chương Hoàng Đế[80]",
    "nienHieu": "Vĩnh Trị (1676-1680)[79] Chính Hòa (1680-1705)[79]",
    "tenHuy": "Lê Duy Hợp[70] Lê Duy Hiệp[79] Lê Duy Cáp[78]",
    "theThu": "con thứ tư Lê Thần Tông[78]",
    "namTriVi": "1675—1705",
    "ten": "Lê Hy Tông[dv]"
  },
  {
    "paperURL": "/wiki/L%C3%AA_D%E1%BB%A5_T%C3%B4ng",
    "mieuHieu": "Dụ Tông[81]",
    "thuyHieu": "Hòa Hoàng Đế[81]",
    "nienHieu": "Vĩnh Thịnh (1706-1719)[80] Bảo Thái (1720-1729)[82]",
    "tenHuy": "Lê Duy Đường[82] Lê Duy Tạo[70]",
    "theThu": "con trưởng Lê Hy Tông[83]",
    "namTriVi": "1705—1729",
    "ten": "Lê Dụ Tông[dw]"
  },
  {
    "paperURL": "/wiki/L%C3%AA_Duy_Ph%C6%B0%E1%BB%9Dng",
    "mieuHieu": "không có",
    "thuyHieu": "Hôn Đức Công",
    "nienHieu": "Vĩnh Khánh (1729-1732)[82]",
    "tenHuy": "Lê Duy Phường[82]",
    "theThu": "con thứ Lê Dụ Tông[82]",
    "namTriVi": "1729—1732",
    "ten": "Lê Duy Phường"
  },
  {
    "paperURL": "/wiki/L%C3%AA_Thu%E1%BA%A7n_T%C3%B4ng",
    "mieuHieu": "Thuần Tông[82]",
    "thuyHieu": "Giản Hoàng Đế[82]",
    "nienHieu": "Long Đức (1732-1735)[82]",
    "tenHuy": "Lê Duy Tường[82] Lê Duy Hỗ[84]",
    "theThu": "con trưởng Lê Dụ Tông[82]",
    "namTriVi": "1732—1735",
    "ten": "Lê Thuần Tông[dx]"
  },
  {
    "paperURL": "/wiki/L%C3%AA_%C3%9D_T%C3%B4ng",
    "mieuHieu": "Ý Tông[85]",
    "thuyHieu": "Huy Hoàng Đế[85]",
    "nienHieu": "Vĩnh Hựu (1735-1740)[86]",
    "tenHuy": "Lê Duy Thận[81] Lê Duy Chấn[87] Lê Duy Hỗ[88]",
    "theThu": "con thứ 11 Lê Dụ Tông[81]",
    "namTriVi": "1735—1740",
    "ten": "Lê Ý Tông[dy]"
  },
  {
    "paperURL": "/wiki/L%C3%AA_Hi%E1%BB%83n_T%C3%B4ng",
    "mieuHieu": "Hiển Tông[89]",
    "thuyHieu": "Vĩnh Hoàng Đế[89]",
    "nienHieu": "Cảnh Hưng (1740-1786)[89]",
    "tenHuy": "Lê Duy Diêu[86] Lê Duy Đào[70]",
    "theThu": "con trưởng Lê Thuần Tông[86]",
    "namTriVi": "1740—1786",
    "ten": "Lê Hiển Tông[dz]"
  },
  {
    "paperURL": "/wiki/L%C3%AA_Chi%C3%AAu_Th%E1%BB%91ng",
    "mieuHieu": "không có[70]",
    "thuyHieu": "Mẫn Hoàng Đế[eb]",
    "nienHieu": "Chiêu Thống (1786-1789)[90]",
    "tenHuy": "Lê Duy Kỳ[90][91] Lê Duy Khiêm[88] Lê Tư Khiêm[70]",
    "theThu": "con Lê Duy Vỹ, cháu đích tôn Lê Hiển Tông[90]",
    "namTriVi": "1786—1789",
    "ten": "Lê Chiêu Thống[ea]"
  },
  {
    "paperURL": "/wiki/Tr%E1%BB%8Bnh_Ki%E1%BB%83m",
    "mieuHieu": "Thế Tổ[61]",
    "thuyHieu": "Minh Khang Thái Vương[61]",
    "nienHieu": "không có[61]",
    "tenHuy": "Trịnh Kiểm[61]",
    "theThu": "con rể Nguyễn Kim[61]",
    "namTriVi": "1545—1570",
    "ten": "Trịnh Kiểm[ed]"
  },
  {
    "paperURL": "/wiki/Tr%E1%BB%8Bnh_C%E1%BB%91i",
    "mieuHieu": "không có[61]",
    "thuyHieu": "Tuấn Đức Hầu, Trung Quốc Công[ef]",
    "nienHieu": "không có[61]",
    "tenHuy": "Trịnh Cối[61]",
    "theThu": "con cả Trịnh Kiểm[61]",
    "namTriVi": "1570—1570",
    "ten": "Trịnh Cối[ee]"
  },
  {
    "paperURL": "/wiki/Tr%E1%BB%8Bnh_T%C3%B9ng",
    "mieuHieu": "Thành Tổ[93]",
    "thuyHieu": "Triết Vương[93]",
    "nienHieu": "không có[93]",
    "tenHuy": "Trịnh Tùng[93]",
    "theThu": "con thứ Trịnh Kiểm, chúa Trịnh đầu tiên[72]",
    "namTriVi": "1570—1623",
    "ten": "Bình An Vương[eg]"
  },
  {
    "paperURL": "/wiki/Tr%E1%BB%8Bnh_Tr%C3%A1ng",
    "mieuHieu": "Văn Tổ[94]",
    "thuyHieu": "Nghị Vương[94]",
    "nienHieu": "không có[94]",
    "tenHuy": "Trịnh Tráng[94]",
    "theThu": "con thứ hai Trịnh Tùng[94]",
    "namTriVi": "1623—1657",
    "ten": "Thanh Đô Vương[eh]"
  },
  {
    "paperURL": "/wiki/Tr%E1%BB%8Bnh_T%E1%BA%A1c",
    "mieuHieu": "Hoằng Tổ[77]",
    "thuyHieu": "Dương Vương[77]",
    "nienHieu": "không có[77]",
    "tenHuy": "Trịnh Tạc[76]",
    "theThu": "con thứ hai Trịnh Tráng[76]",
    "namTriVi": "1657—1682",
    "ten": "Tây Định Vương[ei]"
  },
  {
    "paperURL": "/wiki/Tr%E1%BB%8Bnh_C%C4%83n",
    "mieuHieu": "Chiêu Tổ[77]",
    "thuyHieu": "Khang Vương[77]",
    "nienHieu": "không có[77]",
    "tenHuy": "Trịnh Căn[79]",
    "theThu": "con trưởng Trịnh Tạc[79]",
    "namTriVi": "1682—1709",
    "ten": "Định Nam Vương[ej]"
  },
  {
    "paperURL": "/wiki/Tr%E1%BB%8Bnh_C%C6%B0%C6%A1ng",
    "mieuHieu": "Hy Tổ[77]",
    "thuyHieu": "Nhân Vương[77]",
    "nienHieu": "không có[77]",
    "tenHuy": "Trịnh Cương[80]",
    "theThu": "chắt của Trịnh Căn, cháu Trịnh Vịnh, con Trịnh Bính[80]",
    "namTriVi": "1709—1729",
    "ten": "An Đô Vương[ek]"
  },
  {
    "paperURL": "/wiki/Tr%E1%BB%8Bnh_Giang",
    "mieuHieu": "Dụ Tổ[77]",
    "thuyHieu": "Thuận Vương[77]",
    "nienHieu": "không có[77]",
    "tenHuy": "Trịnh Giang[85] Trịnh Khương[85] Trịnh 𣞪[70]",
    "theThu": "con trưởng Trịnh Cương[81]",
    "namTriVi": "1729—1740",
    "ten": "Uy Nam Vương[el]"
  },
  {
    "paperURL": "/wiki/Tr%E1%BB%8Bnh_Doanh",
    "mieuHieu": "Nghị Tổ[77]",
    "thuyHieu": "Ân Vương[77]",
    "nienHieu": "không có[77]",
    "tenHuy": "Trịnh Doanh[95]",
    "theThu": "con thứ Trịnh Cương, em Trịnh Giang[86]",
    "namTriVi": "1740—1767",
    "ten": "Minh Đô Vương[em]"
  },
  {
    "paperURL": "/wiki/Tr%E1%BB%8Bnh_S%C3%A2m",
    "mieuHieu": "Thánh Tổ[77]",
    "thuyHieu": "Thịnh Vương[96]",
    "nienHieu": "không có[96]",
    "tenHuy": "Trịnh Sâm[96]",
    "theThu": "con trưởng Trịnh Doanh[95]",
    "namTriVi": "1767—1782",
    "ten": "Tĩnh Đô Vương[en]"
  },
  {
    "paperURL": "/wiki/Tr%E1%BB%8Bnh_C%C3%A1n",
    "mieuHieu": "không có[96]",
    "thuyHieu": "Xung Mẫn Vương[97]",
    "nienHieu": "không có[96]",
    "tenHuy": "Trịnh Cán[96]",
    "theThu": "con thứ Trịnh Sâm[96]",
    "namTriVi": "1782—1782",
    "ten": "Điện Đô Vương[eo]"
  },
  {
    "paperURL": "/wiki/Tr%E1%BB%8Bnh_Kh%E1%BA%A3i",
    "mieuHieu": "không có[89]",
    "thuyHieu": "Anh Liệt Linh Vương[97]",
    "nienHieu": "không có[89]",
    "tenHuy": "Trịnh Khải[96] Trịnh Tông[96]",
    "theThu": "con trưởng Trịnh Sâm[96]",
    "namTriVi": "1782—1786",
    "ten": "Đoan Nam Vương[ep]"
  },
  {
    "paperURL": "/wiki/Tr%E1%BB%8Bnh_B%E1%BB%93ng",
    "mieuHieu": "không có[92]",
    "thuyHieu": "Huệ Định Công[er]",
    "nienHieu": "không có[92]",
    "tenHuy": "Trịnh Bồng[89]",
    "theThu": "con Trịnh Giang, anh họ Trịnh Sâm[89]",
    "namTriVi": "1786—1787",
    "ten": "Án Đô Vương[eq]"
  },
  {
    "paperURL": "/wiki/Nguy%E1%BB%85n_Ho%C3%A0ng",
    "mieuHieu": "Liệt Tổ, Thái Tổ[98][ev]",
    "thuyHieu": "Triệu Cơ Tùy Thống Khâm Minh Cung Ý Cần Nghĩa Đạt Lý Hiển Ứng Chiêu Hựu Diệu Linh Gia Dụ Hoàng Đế[98][ew]",
    "nienHieu": "không có[98]",
    "tenHuy": "Nguyễn Hoàng[98]",
    "theThu": "con út Nguyễn Kim[98]",
    "namTriVi": "1558—1613",
    "ten": "Tiên Vương[eu]"
  },
  {
    "paperURL": "/wiki/Nguy%E1%BB%85n_Ph%C3%BAc_Nguy%C3%AAn",
    "mieuHieu": "Tuyên Tổ, Hy Tông[100][ey]",
    "thuyHieu": "Hiển Mô Quang Liệt Ôn Cung Minh Duệ Dực Thiện Tuy Du Hiếu Văn Hoàng Đế[100][ez]",
    "nienHieu": "không có[100]",
    "tenHuy": "Nguyễn Phúc Nguyên[100]",
    "theThu": "con trai thứ sáu Chúa Tiên[100]",
    "namTriVi": "1613—1635",
    "ten": "Sãi Vương[ex] Phật Vương"
  },
  {
    "paperURL": "/wiki/Nguy%E1%BB%85n_Ph%C3%BAc_Lan",
    "mieuHieu": "Thần Tổ, Thần Tông[101][fb]",
    "thuyHieu": "Thừa Cơ Toàn Thống Quân Minh Hùng Nghị Uy Đoán Anh Vũ Hiếu Chiêu Hoàng Đế[101][fc]",
    "nienHieu": "không có[101]",
    "tenHuy": "Nguyễn Phúc Lan[101]",
    "theThu": "con trai thứ hai Chúa Sãi[101]",
    "namTriVi": "1635—1648",
    "ten": "Thượng Vương[fa]"
  },
  {
    "paperURL": "/wiki/Nguy%E1%BB%85n_Ph%C3%BAc_T%E1%BA%A7n",
    "mieuHieu": "Nghị Tổ, Thái Tông[102][fe]",
    "thuyHieu": "Tuyên Uy Kiến Vũ Anh Minh Trang Chính Thánh Đức Thần Công Hiếu Triết Hoàng Đế[102][ff]",
    "nienHieu": "không có[102]",
    "tenHuy": "Nguyễn Phúc Tần[102] Nguyễn Phúc Cần",
    "theThu": "con trai thứ hai Chúa Thượng[102]",
    "namTriVi": "1648—1687",
    "ten": "Hiền Vương[fd]"
  },
  {
    "paperURL": "/wiki/Nguy%E1%BB%85n_Ph%C3%BAc_Th%C3%A1i",
    "mieuHieu": "Anh Tông[103]",
    "thuyHieu": "Thiệu Hư Toản Nghiệp Khoan Hồng Bác Hậu Ôn Huệ Từ Tường Hiếu Nghĩa Hoàng Đế[103][fh]",
    "nienHieu": "không có[103]",
    "tenHuy": "Nguyễn Phúc Thái Nguyễn Phúc Trăn Nguyễn Phúc Ngàn[103]",
    "theThu": "con trai thứ hai Chúa Hiền[103]",
    "namTriVi": "1687—1691",
    "ten": "Nghĩa Vương[fg]"
  },
  {
    "paperURL": "/wiki/Nguy%E1%BB%85n_Ph%C3%BAc_Chu",
    "mieuHieu": "Hiển Tông[104]",
    "thuyHieu": "Anh Mô Hùng Lược Thánh Minh Tuyên Đạt Khoan Từ Nhân Thứ Hiếu Minh Hoàng Đế[104][fj]",
    "nienHieu": "không có[104]",
    "tenHuy": "Nguyễn Phúc Chu Nguyễn Phúc Tùng[104]",
    "theThu": "con trưởng Chúa Nghĩa[104]",
    "namTriVi": "1691—1725",
    "ten": "Minh Vương[fi] Quốc Chúa"
  },
  {
    "paperURL": "/wiki/Nguy%E1%BB%85n_Ph%C3%BAc_Ch%C3%BA",
    "mieuHieu": "Túc Tông[105]",
    "thuyHieu": "Tuyên Quang Thiệu Liệt Tuấn Triết Tĩnh Uyên Kinh Văn Vĩ Vũ Hiếu Ninh Hoàng Đế[105][fl]",
    "nienHieu": "không có[105]",
    "tenHuy": "Nguyễn Phúc Chú Nguyễn Phúc Trú[106] Nguyễn Phúc Thụ Nguyễn Phúc Vượng[105]",
    "theThu": "con trưởng Chúa Minh[105]",
    "namTriVi": "1725—1738",
    "ten": "Ninh Vương[fk]"
  },
  {
    "paperURL": "/wiki/Nguy%E1%BB%85n_Ph%C3%BAc_Kho%C3%A1t",
    "mieuHieu": "Thế Tông[107]",
    "thuyHieu": "Kiền Cương Uy Đoán Thần Nghị Thánh Du Nhân Từ Duệ Trí Hiếu Vũ Hoàng Đế[107]",
    "nienHieu": "không có[107]",
    "tenHuy": "Nguyễn Phúc Khoát[107] Nguyễn Phúc Hiểu",
    "theThu": "con trưởng Chúa Ninh[107]",
    "namTriVi": "1738—1765",
    "ten": "Vũ Vương[fm]"
  },
  {
    "paperURL": "/wiki/Nguy%E1%BB%85n_Ph%C3%BAc_Thu%E1%BA%A7n",
    "mieuHieu": "Duệ Tông[108]",
    "thuyHieu": "Thông Minh Khoan Hậu Anh Mẫn Huệ Hòa Hiếu Định Hoàng Đế[108]",
    "nienHieu": "không có[108]",
    "tenHuy": "Nguyễn Phúc Thuần[108] Nguyễn Phúc Hân",
    "theThu": "con trai thứ 16 Chúa Vũ[108]",
    "namTriVi": "1765—1776",
    "ten": "Định Vương[fn]"
  },
  {
    "paperURL": "/wiki/Nguy%E1%BB%85n_Ph%C3%BAc_D%C6%B0%C6%A1ng",
    "mieuHieu": "không có[108]",
    "thuyHieu": "Cung Mẫn Anh Đoán Huyền Mặc Vĩ Văn Mục Vương[108][fp]",
    "nienHieu": "không có[108]",
    "tenHuy": "Nguyễn Phúc Dương[108]",
    "theThu": "con Nguyễn Phúc Hiệu, cháu nội Chúa Vũ, em con chú với vua Gia Long[108]",
    "namTriVi": "1776—1777",
    "ten": "Tân Chính Vương[fo]"
  },
  {
    "paperURL": "/wiki/Nguy%E1%BB%85n_Nh%E1%BA%A1c",
    "mieuHieu": "không có",
    "thuyHieu": "Minh Đức Hoàng Đế[fq]",
    "nienHieu": "Thái Đức (1778-1788)[110]",
    "tenHuy": "Hồ Nhạc[110] Nguyễn Nhạc[109] Nguyễn Văn Nhạc[111]",
    "theThu": "con trưởng Hồ Phi Phúc, sáng lập triều đại",
    "namTriVi": "1778—1788",
    "ten": "Thái Đức[110]"
  },
  {
    "paperURL": "/wiki/Nguy%E1%BB%85n_Hu%E1%BB%87",
    "mieuHieu": "Thái Tổ",
    "thuyHieu": "Vũ Hoàng Đế[109] Trung Thuần Vương[70][fs]",
    "nienHieu": "Quang Trung (1788-1792)[109]",
    "tenHuy": "Nguyễn Huệ[109] Nguyễn Quang Bình[109] Nguyễn Văn Huệ[111] Hồ Thơm[110]",
    "theThu": "con thứ Hồ Phi Phúc, em Nguyễn Nhạc, con rể Lê Hiển Tông",
    "namTriVi": "1788—1792",
    "ten": "Quang Trung[109]"
  },
  {
    "paperURL": "/wiki/Nguy%E1%BB%85n_Quang_To%E1%BA%A3n",
    "mieuHieu": "không có",
    "thuyHieu": "không có[70][109]",
    "nienHieu": "Cảnh Thịnh (1792-1801)[109] Bảo Hưng (1801-1802)[109]",
    "tenHuy": "Nguyễn Quang Toản[109] Nguyễn Trát[110]",
    "theThu": "con thứ Quang Trung, con rể Lê Hiển Tông",
    "namTriVi": "1792—1802",
    "ten": "Nguyễn Quang Toản[109]"
  },
  {
    "paperURL": "/wiki/Gia_Long",
    "mieuHieu": "Thế Tổ[112]",
    "thuyHieu": "Khai Thiên Hoằng Đạo Lập Kỷ Thùy Thống Thần Văn Thánh Vũ Tuấn Đức Long Công Chí Nhân Đại Hiếu Cao Hoàng Đế[112]",
    "nienHieu": "Gia Long (1802–1820)[112]",
    "tenHuy": "Nguyễn Phúc Ánh[113] Nguyễn Phúc Chủng[113] Nguyễn Phúc Noãn[113]",
    "theThu": "Sáng lập triều đại. Con thứ ba của Nguyễn Phúc Luân, cháu nội Nguyễn Phúc Khoát, con rể Lê Hiển Tông[113]",
    "namTriVi": "1802–1820",
    "ten": "Gia Long[112]"
  },
  {
    "paperURL": "/wiki/Minh_M%E1%BA%A1ng",
    "mieuHieu": "Thánh Tổ[114]",
    "thuyHieu": "Thể Thiên Xương Vận Chí Hiếu Thuần Đức Văn Vũ Minh Đoán Sáng Thuật Đại Thành Hậu Trạch Phong Công Nhân Hoàng Đế[114]",
    "nienHieu": "Minh Mạng (1820–1841)[114]",
    "tenHuy": "Nguyễn Phúc Đảm[115] Nguyễn Phúc Kiểu[115]",
    "theThu": "Con thứ tư Gia Long[115]",
    "namTriVi": "1820–1841",
    "ten": "Minh Mạng[114]"
  },
  {
    "paperURL": "/wiki/Thi%E1%BB%87u_Tr%E1%BB%8B",
    "mieuHieu": "Hiến Tổ[116]",
    "thuyHieu": "Thiệu Thiên Long Vận Chí Thiện Thuần Hiếu Khoan Minh Duệ Đoán Văn Trị Vũ Công Thánh Triết Chương Hoàng Đế[116]",
    "nienHieu": "Thiệu Trị (1841–1847)[116]",
    "tenHuy": "Nguyễn Phúc Miên Tông[117] Nguyễn Phúc Tuyền[117] Nguyễn Phúc Dung[117]",
    "theThu": "Con trưởng Minh Mạng[117]",
    "namTriVi": "1841–1847",
    "ten": "Thiệu Trị[116]"
  },
  {
    "paperURL": "/wiki/T%E1%BB%B1_%C4%90%E1%BB%A9c",
    "mieuHieu": "Dực Tông[118]",
    "thuyHieu": "Thể Thiên Hanh Vận Chí Thành Đạt Hiếu Thể Kiện Đôn Nhân Khiêm Cung Minh Lược Duệ Văn Anh Hoàng Đế[118]",
    "nienHieu": "Tự Đức (1847–1883)[118]",
    "tenHuy": "Nguyễn Phúc Hồng Nhậm[119] Nguyễn Phúc Thì[119]",
    "theThu": "Con thứ Thiệu Trị[119]",
    "namTriVi": "1847–1883",
    "ten": "Tự Đức[118]"
  },
  {
    "paperURL": "/wiki/D%E1%BB%A5c_%C4%90%E1%BB%A9c",
    "mieuHieu": "Cung Tông[fv]",
    "thuyHieu": "Huệ Hoàng Đế[fv]",
    "nienHieu": "không có[120]",
    "tenHuy": "Nguyễn Phúc Ưng Chân[120] Nguyễn Phúc Ưng Ái[120]",
    "theThu": "Con thứ Nguyễn Phúc Hồng Y, cháu nội Thiệu Trị, con nuôi Tự Đức[120]",
    "namTriVi": "1883–1883",
    "ten": "Dục Đức[fu]"
  },
  {
    "paperURL": "/wiki/Hi%E1%BB%87p_H%C3%B2a",
    "mieuHieu": "không có[120]",
    "thuyHieu": "Phế Đế[aw][fw]",
    "nienHieu": "Hiệp Hòa (1883)[120]",
    "tenHuy": "Nguyễn Phúc Hồng Dật[120] Nguyễn Phúc Thăng[120]",
    "theThu": "Con thứ 29 Thiệu Trị[120]",
    "namTriVi": "1883–1883",
    "ten": "Hiệp Hòa[120]"
  },
  {
    "paperURL": "/wiki/Ki%E1%BA%BFn_Ph%C3%BAc",
    "mieuHieu": "Giản Tông[122]",
    "thuyHieu": "Thiệu Đức Chí Hiếu Uyên Duệ Nghị Hoàng Đế[122]",
    "nienHieu": "Kiến Phúc (1883-1884)[121]",
    "tenHuy": "Nguyễn Phúc Ưng Đăng[121]",
    "theThu": "Con thứ Nguyễn Phúc Hồng Cai, cháu nội Thiệu Trị[121]",
    "namTriVi": "1883–1884",
    "ten": "Kiến Phúc[121]"
  },
  {
    "paperURL": "/wiki/H%C3%A0m_Nghi",
    "mieuHieu": "không có[122]",
    "thuyHieu": "Xuất Đế[fx]",
    "nienHieu": "Hàm Nghi (1884–1885)[123]",
    "tenHuy": "Nguyễn Phúc Ưng Lịch[122] Nguyễn Phúc Minh[122]",
    "theThu": "Em trai Kiến Phúc[122]",
    "namTriVi": "1884–1885",
    "ten": "Hàm Nghi[122]"
  },
  {
    "paperURL": "/wiki/%C4%90%E1%BB%93ng_Kh%C3%A1nh",
    "mieuHieu": "Cảnh Tông[125]",
    "thuyHieu": "Hoằng Liệt Thống Thiết Mẫn Huệ Thuần Hoàng Đế[125]",
    "nienHieu": "Đồng Khánh (1885–1889)[125]",
    "tenHuy": "Nguyễn Phúc Ưng Kỷ[124] Nguyễn Phúc Ưng Đường[124] Nguyễn Phúc Ưng Thị[124] Nguyễn Phúc Biện[124] Chánh Mông[fy]",
    "theThu": "Con trưởng Nguyễn Phúc Hồng Cai, anh Kiến Phúc và Hàm Nghi[124]",
    "namTriVi": "1885–1889",
    "ten": "Đồng Khánh[124]"
  },
  {
    "paperURL": "/wiki/Th%C3%A0nh_Th%C3%A1i",
    "mieuHieu": "không có[126]",
    "thuyHieu": "Phế Đế[aw][fz]",
    "nienHieu": "Thành Thái (1889–1907)[126]",
    "tenHuy": "Nguyễn Phúc Bửu Lân[124] Nguyễn Phúc Chiêu[124]",
    "theThu": "Con Dục Đức[124]",
    "namTriVi": "1889–1907",
    "ten": "Thành Thái[124]"
  },
  {
    "paperURL": "/wiki/Duy_T%C3%A2n",
    "mieuHieu": "không có[128]",
    "thuyHieu": "Phế Đế[aw][fz]",
    "nienHieu": "Duy Tân (1907–1916)[128]",
    "tenHuy": "Nguyễn Phúc Vĩnh San[127] Nguyễn Phúc Hoảng[127]",
    "theThu": "Con thứ Thành Thái[127]",
    "namTriVi": "1907–1916",
    "ten": "Duy Tân[127]"
  },
  {
    "paperURL": "/wiki/Kh%E1%BA%A3i_%C4%90%E1%BB%8Bnh",
    "mieuHieu": "Hoằng Tông[129]",
    "thuyHieu": "Tự Thiên Gia Vận Thánh Minh Thần Trí Nhân Hiếu Thành Kính Di Mô Thừa Liệt Tuyên Hoàng Đế[129]",
    "nienHieu": "Khải Định (1916-1925)[129]",
    "tenHuy": "Nguyễn Phúc Bửu Đảo[129]",
    "theThu": "Con trưởng Đồng Khánh[129]",
    "namTriVi": "1916–1925",
    "ten": "Khải Định[129]"
  },
  {
    "paperURL": "/wiki/B%E1%BA%A3o_%C4%90%E1%BA%A1i",
    "mieuHieu": "không có[130]",
    "thuyHieu": "không có[130]",
    "nienHieu": "Bảo Đại (1925–1945)[130]",
    "tenHuy": "Nguyễn Phúc Vĩnh Thụy[130] Nguyễn Phúc Thiển[130]",
    "theThu": "Con Khải Định[130]",
    "namTriVi": "1925–1945",
    "ten": "Bảo Đại[ga]"
  }
]